gmemo/__init__.py
gmemo/__main__.py
gmemo/gmemo_cl.py
gmemo/gmemo_ic.py
gmemo-0.0.1.dist-info/METADATA
gmemo-0.0.1.dist-info/WHEEL
gmemo-0.0.1.dist-info/entry_points.txt
gmemo-0.0.1.dist-info/top_level.txt
gmemo-0.0.1.dist-info/RECORD
