Metadata-Version: 2.1
Name: gmemo
Version: 0.0.1
Summary: Command line application for global memo.
Home-page: https://gitlab.com/kegeppa
Author: kegeppa
Author-email: 
Maintainer: kegeppa
Maintainer-email: 
License: MIT
Platform: UNKNOWN
Classifier: Programming Language :: Python :: 3
Requires-Dist: sicfw (==0.0.3)
